[
  {
    "time": "2025-01-31T15:45:44.663Z",
    "type": "BUY",
    "symbol": "AIXBTUSDC",
    "price": 0.4912,
    "quantity": 508.957654723127
  },
  {
    "time": "2025-01-31T15:45:50.495Z",
    "type": "BUY",
    "symbol": "AIXBTUSDC",
    "price": 0.4912,
    "quantity": 508.957654723127
  },
  {
    "time": "2025-01-31T15:45:56.440Z",
    "type": "BUY",
    "symbol": "AIXBTUSDC",
    "price": 0.4912,
    "quantity": 508.957654723127
  },
  {
    "time": "2025-01-31T15:46:02.292Z",
    "type": "BUY",
    "symbol": "AIXBTUSDC",
    "price": 0.4912,
    "quantity": 508.957654723127
  },
  {
    "time": "2025-01-31T15:46:08.122Z",
    "type": "BUY",
    "symbol": "AIXBTUSDC",
    "price": 0.4912,
    "quantity": 508.957654723127
  },
  {
    "time": "2025-01-31T15:46:13.939Z",
    "type": "BUY",
    "symbol": "AIXBTUSDC",
    "price": 0.4908,
    "quantity": 509.3724531377343
  },
  {
    "time": "2025-01-31T15:46:19.737Z",
    "type": "BUY",
    "symbol": "AIXBTUSDC",
    "price": 0.4908,
    "quantity": 509.3724531377343
  },
  {
    "time": "2025-01-31T15:46:25.569Z",
    "type": "BUY",
    "symbol": "AIXBTUSDC",
    "price": 0.4908,
    "quantity": 509.3724531377343
  },
  {
    "time": "2025-01-31T15:46:31.423Z",
    "type": "BUY",
    "symbol": "AIXBTUSDC",
    "price": 0.4908,
    "quantity": 509.3724531377343
  },
  {
    "time": "2025-02-01T19:43:56.150Z",
    "type": "BUY",
    "symbol": "AIXBTUSDC",
    "price": 0.3693,
    "quantity": 67.6956404007582,
    "profitLoss": 0
  },
  {
    "time": "2025-02-01T19:44:01.948Z",
    "type": "BUY",
    "symbol": "AIXBTUSDC",
    "price": 0.3693,
    "quantity": 67.6956404007582,
    "profitLoss": 0
  },
  {
    "time": "2025-02-01T19:44:07.662Z",
    "type": "BUY",
    "symbol": "AIXBTUSDC",
    "price": 0.3693,
    "quantity": 67.6956404007582,
    "profitLoss": 0
  },
  {
    "time": "2025-02-01T19:44:13.462Z",
    "type": "BUY",
    "symbol": "AIXBTUSDC",
    "price": 0.3693,
    "quantity": 67.6956404007582,
    "profitLoss": 0
  },
  {
    "time": "2025-02-01T19:44:19.200Z",
    "type": "BUY",
    "symbol": "AIXBTUSDC",
    "price": 0.3689,
    "quantity": 67.76904310111141,
    "profitLoss": 0
  },
  {
    "time": "2025-02-01T19:44:24.937Z",
    "type": "BUY",
    "symbol": "AIXBTUSDC",
    "price": 0.3689,
    "quantity": 67.76904310111141,
    "profitLoss": 0
  },
  {
    "time": "2025-02-01T19:44:30.727Z",
    "type": "BUY",
    "symbol": "AIXBTUSDC",
    "price": 0.3689,
    "quantity": 67.76904310111141,
    "profitLoss": 0
  },
  {
    "time": "2025-02-01T19:44:36.552Z",
    "type": "BUY",
    "symbol": "AIXBTUSDC",
    "price": 0.3689,
    "quantity": 67.76904310111141,
    "profitLoss": 0
  },
  {
    "time": "2025-02-01T19:44:42.314Z",
    "type": "BUY",
    "symbol": "AIXBTUSDC",
    "price": 0.3689,
    "quantity": 67.76904310111141,
    "profitLoss": 0
  },
  {
    "time": "2025-02-01T19:44:48.076Z",
    "type": "BUY",
    "symbol": "AIXBTUSDC",
    "price": 0.3686,
    "quantity": 67.82419967444385,
    "profitLoss": 0
  },
  {
    "time": "2025-02-01T19:44:53.888Z",
    "type": "BUY",
    "symbol": "AIXBTUSDC",
    "price": 0.3686,
    "quantity": 67.82419967444385,
    "profitLoss": 0
  },
  {
    "time": "2025-02-01T19:44:59.697Z",
    "type": "BUY",
    "symbol": "AIXBTUSDC",
    "price": 0.3686,
    "quantity": 67.82419967444385,
    "profitLoss": 0
  },
  {
    "time": "2025-02-01T19:45:05.516Z",
    "type": "BUY",
    "symbol": "AIXBTUSDC",
    "price": 0.3686,
    "quantity": 67.82419967444385,
    "profitLoss": 0
  },
  {
    "time": "2025-02-01T19:45:11.283Z",
    "type": "BUY",
    "symbol": "AIXBTUSDC",
    "price": 0.3686,
    "quantity": 67.82419967444385,
    "profitLoss": 0
  },
  {
    "time": "2025-02-01T19:45:17.054Z",
    "type": "BUY",
    "symbol": "AIXBTUSDC",
    "price": 0.3685,
    "quantity": 67.84260515603799,
    "profitLoss": 0
  },
  {
    "time": "2025-02-01T19:45:22.846Z",
    "type": "BUY",
    "symbol": "AIXBTUSDC",
    "price": 0.3685,
    "quantity": 67.84260515603799,
    "profitLoss": 0
  },
  {
    "time": "2025-02-01T19:45:32.907Z",
    "type": "BUY",
    "symbol": "AIXBTUSDC",
    "price": 0.3685,
    "quantity": 67.84260515603799,
    "profitLoss": 0
  },
  {
    "time": "2025-02-01T19:45:38.699Z",
    "type": "BUY",
    "symbol": "AIXBTUSDC",
    "price": 0.3685,
    "quantity": 67.84260515603799,
    "profitLoss": 0
  },
  {
    "time": "2025-02-01T19:45:44.437Z",
    "type": "BUY",
    "symbol": "AIXBTUSDC",
    "price": 0.3685,
    "quantity": 67.84260515603799,
    "profitLoss": 0
  },
  {
    "time": "2025-02-01T19:45:50.241Z",
    "type": "BUY",
    "symbol": "AIXBTUSDC",
    "price": 0.3685,
    "quantity": 67.84260515603799,
    "profitLoss": 0
  },
  {
    "time": "2025-02-01T19:45:56.036Z",
    "type": "BUY",
    "symbol": "AIXBTUSDC",
    "price": 0.3685,
    "quantity": 67.84260515603799,
    "profitLoss": 0
  },
  {
    "time": "2025-02-01T19:46:01.832Z",
    "type": "BUY",
    "symbol": "AIXBTUSDC",
    "price": 0.3685,
    "quantity": 67.84260515603799,
    "profitLoss": 0
  },
  {
    "time": "2025-02-01T19:46:07.610Z",
    "type": "BUY",
    "symbol": "AIXBTUSDC",
    "price": 0.3685,
    "quantity": 67.84260515603799,
    "profitLoss": 0
  },
  {
    "time": "2025-02-01T19:46:13.383Z",
    "type": "BUY",
    "symbol": "AIXBTUSDC",
    "price": 0.3685,
    "quantity": 67.84260515603799,
    "profitLoss": 0
  },
  {
    "time": "2025-02-01T19:46:19.209Z",
    "type": "BUY",
    "symbol": "AIXBTUSDC",
    "price": 0.3685,
    "quantity": 67.84260515603799,
    "profitLoss": 0
  },
  {
    "time": "2025-02-01T19:46:24.933Z",
    "type": "BUY",
    "symbol": "AIXBTUSDC",
    "price": 0.3685,
    "quantity": 67.84260515603799,
    "profitLoss": 0
  },
  {
    "time": "2025-02-01T19:46:30.691Z",
    "type": "BUY",
    "symbol": "AIXBTUSDC",
    "price": 0.3683,
    "quantity": 67.87944610371979,
    "profitLoss": 0
  },
  {
    "time": "2025-02-01T19:46:36.481Z",
    "type": "BUY",
    "symbol": "AIXBTUSDC",
    "price": 0.3683,
    "quantity": 67.87944610371979,
    "profitLoss": 0
  },
  {
    "time": "2025-02-01T19:46:42.246Z",
    "type": "BUY",
    "symbol": "AIXBTUSDC",
    "price": 0.3683,
    "quantity": 67.87944610371979,
    "profitLoss": 0
  },
  {
    "time": "2025-02-01T19:46:48.013Z",
    "type": "BUY",
    "symbol": "AIXBTUSDC",
    "price": 0.3683,
    "quantity": 67.87944610371979,
    "profitLoss": 0
  },
  {
    "time": "2025-02-01T19:46:53.764Z",
    "type": "BUY",
    "symbol": "AIXBTUSDC",
    "price": 0.3683,
    "quantity": 67.87944610371979,
    "profitLoss": 0
  },
  {
    "time": "2025-02-01T19:46:59.499Z",
    "type": "BUY",
    "symbol": "AIXBTUSDC",
    "price": 0.3688,
    "quantity": 67.78741865509761,
    "profitLoss": 0
  },
  {
    "time": "2025-02-01T19:47:05.306Z",
    "type": "BUY",
    "symbol": "AIXBTUSDC",
    "price": 0.3688,
    "quantity": 67.78741865509761,
    "profitLoss": 0
  },
  {
    "time": "2025-02-01T19:47:11.111Z",
    "type": "BUY",
    "symbol": "AIXBTUSDC",
    "price": 0.3688,
    "quantity": 67.78741865509761,
    "profitLoss": 0
  },
  {
    "time": "2025-02-01T19:47:16.858Z",
    "type": "BUY",
    "symbol": "AIXBTUSDC",
    "price": 0.3688,
    "quantity": 67.78741865509761,
    "profitLoss": 0
  },
  {
    "time": "2025-02-01T19:47:22.607Z",
    "type": "BUY",
    "symbol": "AIXBTUSDC",
    "price": 0.3688,
    "quantity": 67.78741865509761,
    "profitLoss": 0
  },
  {
    "time": "2025-02-01T19:47:28.379Z",
    "type": "BUY",
    "symbol": "AIXBTUSDC",
    "price": 0.3688,
    "quantity": 67.78741865509761,
    "profitLoss": 0
  },
  {
    "time": "2025-02-01T19:47:34.171Z",
    "type": "BUY",
    "symbol": "AIXBTUSDC",
    "price": 0.3688,
    "quantity": 67.78741865509761,
    "profitLoss": 0
  },
  {
    "time": "2025-02-01T19:47:40.330Z",
    "type": "BUY",
    "symbol": "AIXBTUSDC",
    "price": 0.3688,
    "quantity": 67.78741865509761,
    "profitLoss": 0
  },
  {
    "time": "2025-02-01T19:47:46.083Z",
    "type": "BUY",
    "symbol": "AIXBTUSDC",
    "price": 0.3688,
    "quantity": 67.78741865509761,
    "profitLoss": 0
  },
  {
    "time": "2025-02-01T19:47:51.862Z",
    "type": "BUY",
    "symbol": "AIXBTUSDC",
    "price": 0.3688,
    "quantity": 67.78741865509761,
    "profitLoss": 0
  },
  {
    "time": "2025-02-01T19:47:57.672Z",
    "type": "BUY",
    "symbol": "AIXBTUSDC",
    "price": 0.3688,
    "quantity": 67.78741865509761,
    "profitLoss": 0
  },
  {
    "time": "2025-02-01T19:48:08.043Z",
    "type": "BUY",
    "symbol": "AIXBTUSDC",
    "price": 0.3688,
    "quantity": 67.78741865509761,
    "profitLoss": 0
  },
  {
    "time": "2025-02-01T19:48:13.814Z",
    "type": "BUY",
    "symbol": "AIXBTUSDC",
    "price": 0.3706,
    "quantity": 67.45817593092283,
    "profitLoss": 0
  },
  {
    "time": "2025-02-01T19:48:19.569Z",
    "type": "BUY",
    "symbol": "AIXBTUSDC",
    "price": 0.3706,
    "quantity": 67.45817593092283,
    "profitLoss": 0
  },
  {
    "time": "2025-02-01T19:48:25.339Z",
    "type": "BUY",
    "symbol": "AIXBTUSDC",
    "price": 0.3706,
    "quantity": 67.45817593092283,
    "profitLoss": 0
  },
  {
    "time": "2025-02-01T19:48:31.060Z",
    "type": "BUY",
    "symbol": "AIXBTUSDC",
    "price": 0.3706,
    "quantity": 67.45817593092283,
    "profitLoss": 0
  },
  {
    "time": "2025-02-01T19:48:36.836Z",
    "type": "BUY",
    "symbol": "AIXBTUSDC",
    "price": 0.3706,
    "quantity": 67.45817593092283,
    "profitLoss": 0
  },
  {
    "time": "2025-02-01T19:48:42.629Z",
    "type": "BUY",
    "symbol": "AIXBTUSDC",
    "price": 0.3704,
    "quantity": 67.49460043196544,
    "profitLoss": 0
  },
  {
    "time": "2025-02-02T17:20:46.723Z",
    "type": "BUY",
    "symbol": "TRUMPUSDC",
    "price": 19.75,
    "quantity": 1.2658227848101267,
    "profitLoss": 0
  },
  {
    "time": "2025-02-02T17:20:51.615Z",
    "type": "BUY",
    "symbol": "TRUMPUSDC",
    "price": 19.74,
    "quantity": 1.2664640324214793,
    "profitLoss": 0
  }
]