[
  {
    "time": "2025-02-04T07:47:27.095Z",
    "type": "BUY",
    "symbol": "DOGEUSDC",
    "price": 0.25914,
    "quantity": 169.79239021378407,
    "profitLoss": 0
  },
  {
    "time": "2025-02-04T21:36:55.185Z",
    "type": "BUY",
    "symbol": "DOGEUSDC",
    "price": 0.25732,
    "quantity": 170.9933157158402,
    "profitLoss": 0
  },
  {
    "time": "2025-02-04T21:37:53.014Z",
    "type": "BUY",
    "symbol": "DOGEUSDC",
    "price": 0.25756,
    "quantity": 170.83398043174404,
    "profitLoss": 0
  },
  {
    "time": "2025-02-04T21:43:52.691Z",
    "type": "BUY",
    "symbol": "BTCUSDC",
    "price": 96692,
    "quantity": 0.0002548297687502586,
    "profitLoss": 0
  },
  {
    "time": "2025-02-04T21:43:52.779Z",
    "type": "BUY",
    "symbol": "BTCUSDC",
    "price": 96692,
    "quantity": 0.0002548297687502586,
    "profitLoss": 0
  },
  {
    "time": "2025-02-05T11:32:54.704Z",
    "type": "BUY",
    "symbol": "ACTUSDC",
    "price": 0.2183,
    "quantity": 63.208428767750796,
    "profitLoss": 0
  },
  {
    "time": "2025-02-05T11:32:54.824Z",
    "type": "BUY",
    "symbol": "ACTUSDC",
    "price": 0.2183,
    "quantity": 63.208428767750796,
    "profitLoss": 0
  },
  {
    "time": "2025-02-05T11:42:36.409Z",
    "type": "BUY",
    "symbol": "ACTUSDC",
    "price": 0.2196,
    "quantity": 200.36429872495447,
    "profitLoss": 0
  },
  {
    "time": "2025-02-05T11:42:36.442Z",
    "type": "BUY",
    "symbol": "ACTUSDC",
    "price": 0.2196,
    "quantity": 200.36429872495447,
    "profitLoss": 0
  },
  {
    "time": "2025-02-05T11:44:25.788Z",
    "type": "BUY",
    "symbol": "ACTUSDC",
    "price": 0.2196,
    "quantity": 112.20400728597451,
    "profitLoss": 0
  },
  {
    "time": "2025-02-05T11:44:25.840Z",
    "type": "BUY",
    "symbol": "ACTUSDC",
    "price": 0.2196,
    "quantity": 112.20400728597451,
    "profitLoss": 0
  },
  {
    "time": "2025-02-05T11:57:32.858Z",
    "type": "BUY",
    "symbol": "ACTUSDC",
    "price": 0.2188,
    "quantity": 63.06398537477148,
    "profitLoss": 0
  },
  {
    "time": "2025-02-05T11:58:32.799Z",
    "type": "BUY",
    "symbol": "ACTUSDC",
    "price": 0.2194,
    "quantity": 35.219252506836824,
    "profitLoss": 0
  },
  {
    "time": "2025-02-05T12:00:59.507Z",
    "type": "BUY",
    "symbol": "ACTUSDC",
    "price": 0.2193,
    "quantity": 19.731774920200632,
    "profitLoss": 0
  },
  {
    "time": "2025-02-05T12:00:59.533Z",
    "type": "BUY",
    "symbol": "ACTUSDC",
    "price": 0.2193,
    "quantity": 19.731774920200632,
    "profitLoss": 0
  },
  {
    "time": "2025-02-05T12:02:07.409Z",
    "type": "BUY",
    "symbol": "ACTUSDC",
    "price": 0.2193,
    "quantity": 11.049793955312357,
    "profitLoss": 0
  },
  {
    "time": "2025-02-05T12:02:07.477Z",
    "type": "BUY",
    "symbol": "ACTUSDC",
    "price": 0.2193,
    "quantity": 11.049793955312357,
    "profitLoss": 0
  },
  {
    "time": "2025-02-05T12:03:07.428Z",
    "type": "BUY",
    "symbol": "ACTUSDC",
    "price": 0.2173,
    "quantity": 6.244837073465254,
    "profitLoss": 0
  },
  {
    "time": "2025-02-05T12:03:07.445Z",
    "type": "BUY",
    "symbol": "ACTUSDC",
    "price": 0.2173,
    "quantity": 6.244837073465254,
    "profitLoss": 0
  }
]